MANIFEST.in
README.txt
collective.webrichtlijnen-configure.zcml
setup.cfg
setup.py
collective/__init__.py
collective.webrichtlijnen.egg-info/PKG-INFO
collective.webrichtlijnen.egg-info/SOURCES.txt
collective.webrichtlijnen.egg-info/dependency_links.txt
collective.webrichtlijnen.egg-info/entry_points.txt
collective.webrichtlijnen.egg-info/namespace_packages.txt
collective.webrichtlijnen.egg-info/not-zip-safe
collective.webrichtlijnen.egg-info/paster_plugins.txt
collective.webrichtlijnen.egg-info/requires.txt
collective.webrichtlijnen.egg-info/top_level.txt
collective/webrichtlijnen/__init__.py
collective/webrichtlijnen/configure.zcml
collective/webrichtlijnen/overrides.zcml
collective/webrichtlijnen/profiles.zcml
collective/webrichtlijnen/setuphandlers.py
collective/webrichtlijnen/skins.zcml
collective/webrichtlijnen/webrichtlijnen.txt
collective/webrichtlijnen/browser/__init__.py
collective/webrichtlijnen/browser/accessibility_fontsize.pt
collective/webrichtlijnen/browser/configure.zcml
collective/webrichtlijnen/browser/document_actions.pt
collective/webrichtlijnen/browser/interfaces.py
collective/webrichtlijnen/browser/personal_bar.pt
collective/webrichtlijnen/browser/searchbox.pt
collective/webrichtlijnen/browser/sections.pt
collective/webrichtlijnen/browser/viewlets.py
collective/webrichtlijnen/browser/images/README.txt
collective/webrichtlijnen/browser/stylesheets/README.txt
collective/webrichtlijnen/browser/stylesheets/main.css
collective/webrichtlijnen/profiles/default/actions.xml
collective/webrichtlijnen/profiles/default/collective.webrichtlijnen_various.txt
collective/webrichtlijnen/profiles/default/cssregistry.xml
collective/webrichtlijnen/profiles/default/import_steps.xml
collective/webrichtlijnen/profiles/default/jsregistry.xml
collective/webrichtlijnen/profiles/default/metadata.xml
collective/webrichtlijnen/profiles/default/skins.xml
collective/webrichtlijnen/skins/collective_webrichtlijnen_custom_templates/CONTENT.txt
collective/webrichtlijnen/skins/collective_webrichtlijnen_custom_templates/accessibility-info.pt
collective/webrichtlijnen/skins/collective_webrichtlijnen_custom_templates/event_view.pt
collective/webrichtlijnen/skins/collective_webrichtlijnen_custom_templates/global_statusmessage.pt
collective/webrichtlijnen/skins/collective_webrichtlijnen_custom_templates/main_template.pt
collective/webrichtlijnen/skins/collective_webrichtlijnen_custom_templates/member_search_form.pt
