Metadata-Version: 1.0
Name: collective.webrichtlijnen
Version: 1.1.2
Summary: A theme product for the Dutch web guidelines.
Home-page: http://pypi.python.org/pypi/collective.webrichtlijnen/
Author: Kim Chee Leong
Author-email: leong@gw20e.com
License: GPL
Keywords: plone theme dutch web guidelines webrichtlijnen
Platform: UNKNOWN
Classifier: Framework :: Plone
Classifier: Programming Language :: Python
Classifier: Topic :: Software Development :: Libraries :: Python Modules
